[
  {
    "actual_time": null, 
    "alliances": {
      "blue": {
        "dq_team_keys": [], 
        "score": 92, 
        "surrogate_team_keys": [], 
        "team_keys": [
          "frc3015", 
          "frc5719", 
          "frc4476"
        ]
      }, 
      "red": {
        "dq_team_keys": [], 
        "score": 124, 
        "surrogate_team_keys": [], 
        "team_keys": [
          "frc1114", 
          "frc7509", 
          "frc3683"
        ]
      }
    }, 
    "comp_level": "f", 
    "event_key": "2019onha2", 
    "key": "2019onha2_f1m1", 
    "match_number": 1, 
    "post_result_time": null, 
    "predicted_time": null, 
    "score_breakdown": null, 
    "set_number": 1, 
    "time": null, 
    "videos": [
      {
        "key": "GJ8roVb5eRk", 
        "type": "youtube"
      }
    ], 
    "winning_alliance": "red"
  }, 
  {
    "actual_time": null, 
    "alliances": {
      "blue": {
        "dq_team_keys": [], 
        "score": 80, 
        "surrogate_team_keys": [], 
        "team_keys": [
          "frc3015", 
          "frc5719", 
          "frc4476"
        ]
      }, 
      "red": {
        "dq_team_keys": [], 
        "score": 76, 
        "surrogate_team_keys": [], 
        "team_keys": [
          "frc1114", 
          "frc7509", 
          "frc3683"
        ]
      }
    }, 
    "comp_level": "f", 
    "event_key": "2019onha2", 
    "key": "2019onha2_f1m2", 
    "match_number": 2, 
    "post_result_time": null, 
    "predicted_time": null, 
    "score_breakdown": null, 
    "set_number": 1, 
    "time": null, 
    "videos": [
      {
        "key": "laocQ32s_5g", 
        "type": "youtube"
      }
    ], 
    "winning_alliance": "blue"
  }, 
  {
    "actual_time": null, 
    "alliances": {
      "blue": {
        "dq_team_keys": [], 
        "score": 87, 
        "surrogate_team_keys": [], 
        "team_keys": [
          "frc3015", 
          "frc5719", 
          "frc4476"
        ]
      }, 
      "red": {
        "dq_team_keys": [], 
        "score": 109, 
        "surrogate_team_keys": [], 
        "team_keys": [
          "frc1114", 
          "frc7509", 
          "frc3683"
        ]
      }
    }, 
    "comp_level": "f", 
    "event_key": "2019onha2", 
    "key": "2019onha2_f1m3", 
    "match_number": 3, 
    "post_result_time": null, 
    "predicted_time": null, 
    "score_breakdown": null, 
    "set_number": 1, 
    "time": null, 
    "videos": [
      {
        "key": "aWtESmRqExk", 
        "type": "youtube"
      }
    ], 
    "winning_alliance": "red"
  }, 
  {
    "actual_time": null, 
    "alliances": {
      "blue": {
        "dq_team_keys": [], 
        "score": 56, 
        "surrogate_team_keys": [], 
        "team_keys": [
          "frc4343", 
          "frc7623", 
          "frc1360"
        ]
      }, 
      "red": {
        "dq_team_keys": [], 
        "score": 90, 
        "surrogate_team_keys": [], 
        "team_keys": [
          "frc1114", 
          "frc7509", 
          "frc3683"
        ]
      }
    }, 
    "comp_level": "qf", 
    "event_key": "2019onha2", 
    "key": "2019onha2_qf1m1", 
    "match_number": 1, 
    "post_result_time": null, 
    "predicted_time": null, 
    "score_breakdown": null, 
    "set_number": 1, 
    "time": null, 
    "videos": [
      {
        "key": "fzEm0ZNMNSU", 
        "type": "youtube"
      }
    ], 
    "winning_alliance": "red"
  }, 
  {
    "actual_time": null, 
    "alliances": {
      "blue": {
        "dq_team_keys": [], 
        "score": 47, 
        "surrogate_team_keys": [], 
        "team_keys": [
          "frc4343", 
          "frc7623", 
          "frc1360"
        ]
      }, 
      "red": {
        "dq_team_keys": [], 
        "score": 99, 
        "surrogate_team_keys": [], 
        "team_keys": [
          "frc1114", 
          "frc7509", 
          "frc3683"
        ]
      }
    }, 
    "comp_level": "qf", 
    "event_key": "2019onha2", 
    "key": "2019onha2_qf1m2", 
    "match_number": 2, 
    "post_result_time": null, 
    "predicted_time": null, 
    "score_breakdown": null, 
    "set_number": 1, 
    "time": null, 
    "videos": [
      {
        "key": "dbGKJZQ-4zA", 
        "type": "youtube"
      }
    ], 
    "winning_alliance": "red"
  }, 
  {
    "actual_time": null, 
    "alliances": {
      "blue": {
        "dq_team_keys": [], 
        "score": 57, 
        "surrogate_team_keys": [], 
        "team_keys": [
          "frc3739", 
          "frc1075", 
          "frc5409"
        ]
      }, 
      "red": {
        "dq_team_keys": [], 
        "score": 63, 
        "surrogate_team_keys": [], 
        "team_keys": [
          "frc1241", 
          "frc4992", 
          "frc4678"
        ]
      }
    }, 
    "comp_level": "qf", 
    "event_key": "2019onha2", 
    "key": "2019onha2_qf2m1", 
    "match_number": 1, 
    "post_result_time": null, 
    "predicted_time": null, 
    "score_breakdown": null, 
    "set_number": 2, 
    "time": null, 
    "videos": [
      {
        "key": "ck8hcp_8Cp0", 
        "type": "youtube"
      }
    ], 
    "winning_alliance": "red"
  }, 
  {
    "actual_time": null, 
    "alliances": {
      "blue": {
        "dq_team_keys": [], 
        "score": 57, 
        "surrogate_team_keys": [], 
        "team_keys": [
          "frc3739", 
          "frc1075", 
          "frc5409"
        ]
      }, 
      "red": {
        "dq_team_keys": [], 
        "score": 52, 
        "surrogate_team_keys": [], 
        "team_keys": [
          "frc1241", 
          "frc4992", 
          "frc4678"
        ]
      }
    }, 
    "comp_level": "qf", 
    "event_key": "2019onha2", 
    "key": "2019onha2_qf2m2", 
    "match_number": 2, 
    "post_result_time": null, 
    "predicted_time": null, 
    "score_breakdown": null, 
    "set_number": 2, 
    "time": null, 
    "videos": [
      {
        "key": "vtlihSOmyJE", 
        "type": "youtube"
      }
    ], 
    "winning_alliance": "blue"
  }, 
  {
    "actual_time": null, 
    "alliances": {
      "blue": {
        "dq_team_keys": [], 
        "score": 74, 
        "surrogate_team_keys": [], 
        "team_keys": [
          "frc3739", 
          "frc1075", 
          "frc5409"
        ]
      }, 
      "red": {
        "dq_team_keys": [], 
        "score": 47, 
        "surrogate_team_keys": [], 
        "team_keys": [
          "frc1241", 
          "frc7480", 
          "frc4678"
        ]
      }
    }, 
    "comp_level": "qf", 
    "event_key": "2019onha2", 
    "key": "2019onha2_qf2m3", 
    "match_number": 3, 
    "post_result_time": null, 
    "predicted_time": null, 
    "score_breakdown": null, 
    "set_number": 2, 
    "time": null, 
    "videos": [
      {
        "key": "y8mZRzNtGdM", 
        "type": "youtube"
      }
    ], 
    "winning_alliance": "blue"
  }, 
  {
    "actual_time": null, 
    "alliances": {
      "blue": {
        "dq_team_keys": [], 
        "score": 51, 
        "surrogate_team_keys": [], 
        "team_keys": [
          "frc2702", 
          "frc7022", 
          "frc1285"
        ]
      }, 
      "red": {
        "dq_team_keys": [], 
        "score": 92, 
        "surrogate_team_keys": [], 
        "team_keys": [
          "frc3015", 
          "frc5719", 
          "frc4476"
        ]
      }
    }, 
    "comp_level": "qf", 
    "event_key": "2019onha2", 
    "key": "2019onha2_qf3m1", 
    "match_number": 1, 
    "post_result_time": null, 
    "predicted_time": null, 
    "score_breakdown": null, 
    "set_number": 3, 
    "time": null, 
    "videos": [], 
    "winning_alliance": "red"
  }, 
  {
    "actual_time": null, 
    "alliances": {
      "blue": {
        "dq_team_keys": [], 
        "score": 54, 
        "surrogate_team_keys": [], 
        "team_keys": [
          "frc2609", 
          "frc7022", 
          "frc2702"
        ]
      }, 
      "red": {
        "dq_team_keys": [], 
        "score": 90, 
        "surrogate_team_keys": [], 
        "team_keys": [
          "frc3015", 
          "frc5719", 
          "frc4476"
        ]
      }
    }, 
    "comp_level": "qf", 
    "event_key": "2019onha2", 
    "key": "2019onha2_qf3m2", 
    "match_number": 2, 
    "post_result_time": null, 
    "predicted_time": null, 
    "score_breakdown": null, 
    "set_number": 3, 
    "time": null, 
    "videos": [
      {
        "key": "uI2Y6Ytbno4", 
        "type": "youtube"
      }, 
      {
        "key": "vtlihSOmyJE", 
        "type": "youtube"
      }
    ], 
    "winning_alliance": "red"
  }, 
  {
    "actual_time": null, 
    "alliances": {
      "blue": {
        "dq_team_keys": [], 
        "score": 57, 
        "surrogate_team_keys": [], 
        "team_keys": [
          "frc9985", 
          "frc2013", 
          "frc865"
        ]
      }, 
      "red": {
        "dq_team_keys": [], 
        "score": 72, 
        "surrogate_team_keys": [], 
        "team_keys": [
          "frc4917", 
          "frc1310", 
          "frc6336"
        ]
      }
    }, 
    "comp_level": "qf", 
    "event_key": "2019onha2", 
    "key": "2019onha2_qf4m1", 
    "match_number": 1, 
    "post_result_time": null, 
    "predicted_time": null, 
    "score_breakdown": null, 
    "set_number": 4, 
    "time": null, 
    "videos": [
      {
        "key": "sg-b-ISX8Dg", 
        "type": "youtube"
      }
    ], 
    "winning_alliance": "red"
  }, 
  {
    "actual_time": null, 
    "alliances": {
      "blue": {
        "dq_team_keys": [], 
        "score": 71, 
        "surrogate_team_keys": [], 
        "team_keys": [
          "frc9985", 
          "frc2013", 
          "frc865"
        ]
      }, 
      "red": {
        "dq_team_keys": [], 
        "score": 54, 
        "surrogate_team_keys": [], 
        "team_keys": [
          "frc4917", 
          "frc6336", 
          "frc1310"
        ]
      }
    }, 
    "comp_level": "qf", 
    "event_key": "2019onha2", 
    "key": "2019onha2_qf4m2", 
    "match_number": 2, 
    "post_result_time": null, 
    "predicted_time": null, 
    "score_breakdown": null, 
    "set_number": 4, 
    "time": null, 
    "videos": [
      {
        "key": "t-wyhLJ0fVM", 
        "type": "youtube"
      }, 
      {
        "key": "V_AWchtIGX0", 
        "type": "youtube"
      }
    ], 
    "winning_alliance": "blue"
  }, 
  {
    "actual_time": null, 
    "alliances": {
      "blue": {
        "dq_team_keys": [], 
        "score": 62, 
        "surrogate_team_keys": [], 
        "team_keys": [
          "frc9985", 
          "frc2013", 
          "frc865"
        ]
      }, 
      "red": {
        "dq_team_keys": [], 
        "score": 62, 
        "surrogate_team_keys": [], 
        "team_keys": [
          "frc4917", 
          "frc6336", 
          "frc1310"
        ]
      }
    }, 
    "comp_level": "qf", 
    "event_key": "2019onha2", 
    "key": "2019onha2_qf4m3", 
    "match_number": 3, 
    "post_result_time": null, 
    "predicted_time": null, 
    "score_breakdown": null, 
    "set_number": 4, 
    "time": null, 
    "videos": [
      {
        "key": "sg-b-ISX8Dg", 
        "type": "youtube"
      }
    ], 
    "winning_alliance": ""
  }, 
  {
    "actual_time": null, 
    "alliances": {
      "blue": {
        "dq_team_keys": [], 
        "score": 41, 
        "surrogate_team_keys": [], 
        "team_keys": [
          "frc7480", 
          "frc1241", 
          "frc4992"
        ]
      }, 
      "red": {
        "dq_team_keys": [], 
        "score": 53, 
        "surrogate_team_keys": [], 
        "team_keys": [
          "frc2702", 
          "frc4678", 
          "frc2604"
        ]
      }
    }, 
    "comp_level": "qm", 
    "event_key": "2019onha2", 
    "key": "2019onha2_qm1", 
    "match_number": 1, 
    "post_result_time": null, 
    "predicted_time": 1573392600, 
    "score_breakdown": null, 
    "set_number": 1, 
    "time": 1573392600, 
    "videos": [
      {
        "key": "vdfL9WcGn7s", 
        "type": "youtube"
      }
    ], 
    "winning_alliance": "red"
  }, 
  {
    "actual_time": null, 
    "alliances": {
      "blue": {
        "dq_team_keys": [], 
        "score": 49, 
        "surrogate_team_keys": [], 
        "team_keys": [
          "frc2702", 
          "frc9986", 
          "frc1285"
        ]
      }, 
      "red": {
        "dq_team_keys": [], 
        "score": 73, 
        "surrogate_team_keys": [], 
        "team_keys": [
          "frc4917", 
          "frc7022", 
          "frc1360"
        ]
      }
    }, 
    "comp_level": "qm", 
    "event_key": "2019onha2", 
    "key": "2019onha2_qm10", 
    "match_number": 10, 
    "post_result_time": null, 
    "predicted_time": 1573396920, 
    "score_breakdown": null, 
    "set_number": 1, 
    "time": 1573396920, 
    "videos": [
      {
        "key": "oU9bmnmInrw", 
        "type": "youtube"
      }
    ], 
    "winning_alliance": "red"
  }, 
  {
    "actual_time": null, 
    "alliances": {
      "blue": {
        "dq_team_keys": [], 
        "score": 82, 
        "surrogate_team_keys": [], 
        "team_keys": [
          "frc865", 
          "frc1075", 
          "frc3015"
        ]
      }, 
      "red": {
        "dq_team_keys": [], 
        "score": 66, 
        "surrogate_team_keys": [], 
        "team_keys": [
          "frc1241", 
          "frc7623", 
          "frc1114"
        ]
      }
    }, 
    "comp_level": "qm", 
    "event_key": "2019onha2", 
    "key": "2019onha2_qm11", 
    "match_number": 11, 
    "post_result_time": null, 
    "predicted_time": 1573397400, 
    "score_breakdown": null, 
    "set_number": 1, 
    "time": 1573397400, 
    "videos": [
      {
        "key": "c1SL-5Uboxw", 
        "type": "youtube"
      }
    ], 
    "winning_alliance": "blue"
  }, 
  {
    "actual_time": null, 
    "alliances": {
      "blue": {
        "dq_team_keys": [], 
        "score": 53, 
        "surrogate_team_keys": [], 
        "team_keys": [
          "frc2013", 
          "frc5912", 
          "frc4992"
        ]
      }, 
      "red": {
        "dq_team_keys": [], 
        "score": 25, 
        "surrogate_team_keys": [], 
        "team_keys": [
          "frc6336", 
          "frc2702", 
          "frc3161"
        ]
      }
    }, 
    "comp_level": "qm", 
    "event_key": "2019onha2", 
    "key": "2019onha2_qm12", 
    "match_number": 12, 
    "post_result_time": null, 
    "predicted_time": 1573397880, 
    "score_breakdown": null, 
    "set_number": 1, 
    "time": 1573397880, 
    "videos": [
      {
        "key": "X6_eZA7RqJM", 
        "type": "youtube"
      }
    ], 
    "winning_alliance": "blue"
  }, 
  {
    "actual_time": null, 
    "alliances": {
      "blue": {
        "dq_team_keys": [], 
        "score": 53, 
        "surrogate_team_keys": [], 
        "team_keys": [
          "frc2604", 
          "frc4917", 
          "frc2609"
        ]
      }, 
      "red": {
        "dq_team_keys": [], 
        "score": 66, 
        "surrogate_team_keys": [], 
        "team_keys": [
          "frc3683", 
          "frc4343", 
          "frc9985"
        ]
      }
    }, 
    "comp_level": "qm", 
    "event_key": "2019onha2", 
    "key": "2019onha2_qm13", 
    "match_number": 13, 
    "post_result_time": null, 
    "predicted_time": 1573398360, 
    "score_breakdown": null, 
    "set_number": 1, 
    "time": 1573398360, 
    "videos": [
      {
        "key": "PunjdE_6CQQ", 
        "type": "youtube"
      }
    ], 
    "winning_alliance": "red"
  }, 
  {
    "actual_time": null, 
    "alliances": {
      "blue": {
        "dq_team_keys": [], 
        "score": 45, 
        "surrogate_team_keys": [], 
        "team_keys": [
          "frc1360", 
          "frc1310", 
          "frc7480"
        ]
      }, 
      "red": {
        "dq_team_keys": [], 
        "score": 89, 
        "surrogate_team_keys": [], 
        "team_keys": [
          "frc5719", 
          "frc5409", 
          "frc3739"
        ]
      }
    }, 
    "comp_level": "qm", 
    "event_key": "2019onha2", 
    "key": "2019onha2_qm14", 
    "match_number": 14, 
    "post_result_time": null, 
    "predicted_time": 1573398840, 
    "score_breakdown": null, 
    "set_number": 1, 
    "time": 1573398840, 
    "videos": [
      {
        "key": "qGGfifcX5Vc", 
        "type": "youtube"
      }
    ], 
    "winning_alliance": "red"
  }, 
  {
    "actual_time": null, 
    "alliances": {
      "blue": {
        "dq_team_keys": [], 
        "score": 55, 
        "surrogate_team_keys": [], 
        "team_keys": [
          "frc4678", 
          "frc9986", 
          "frc7509"
        ]
      }, 
      "red": {
        "dq_team_keys": [], 
        "score": 72, 
        "surrogate_team_keys": [], 
        "team_keys": [
          "frc4476", 
          "frc1285", 
          "frc7022"
        ]
      }
    }, 
    "comp_level": "qm", 
    "event_key": "2019onha2", 
    "key": "2019onha2_qm15", 
    "match_number": 15, 
    "post_result_time": null, 
    "predicted_time": 1573399320, 
    "score_breakdown": null, 
    "set_number": 1, 
    "time": 1573399320, 
    "videos": [
      {
        "key": "V1ngy_jHUr4", 
        "type": "youtube"
      }
    ], 
    "winning_alliance": "red"
  }, 
  {
    "actual_time": null, 
    "alliances": {
      "blue": {
        "dq_team_keys": [], 
        "score": 81, 
        "surrogate_team_keys": [], 
        "team_keys": [
          "frc1114", 
          "frc4917", 
          "frc3739"
        ]
      }, 
      "red": {
        "dq_team_keys": [], 
        "score": 56, 
        "surrogate_team_keys": [], 
        "team_keys": [
          "frc3161", 
          "frc1241", 
          "frc5912"
        ]
      }
    }, 
    "comp_level": "qm", 
    "event_key": "2019onha2", 
    "key": "2019onha2_qm16", 
    "match_number": 16, 
    "post_result_time": null, 
    "predicted_time": 1573399800, 
    "score_breakdown": null, 
    "set_number": 1, 
    "time": 1573399800, 
    "videos": [
      {
        "key": "KO-qyPrYwbQ", 
        "type": "youtube"
      }
    ], 
    "winning_alliance": "blue"
  }, 
  {
    "actual_time": null, 
    "alliances": {
      "blue": {
        "dq_team_keys": [], 
        "score": 58, 
        "surrogate_team_keys": [], 
        "team_keys": [
          "frc1075", 
          "frc9985", 
          "frc1285"
        ]
      }, 
      "red": {
        "dq_team_keys": [], 
        "score": 46, 
        "surrogate_team_keys": [], 
        "team_keys": [
          "frc7509", 
          "frc6336", 
          "frc4992"
        ]
      }
    }, 
    "comp_level": "qm", 
    "event_key": "2019onha2", 
    "key": "2019onha2_qm17", 
    "match_number": 17, 
    "post_result_time": null, 
    "predicted_time": 1573400280, 
    "score_breakdown": null, 
    "set_number": 1, 
    "time": 1573400280, 
    "videos": [
      {
        "key": "oIYqIF2AQY8", 
        "type": "youtube"
      }
    ], 
    "winning_alliance": "blue"
  }, 
  {
    "actual_time": null, 
    "alliances": {
      "blue": {
        "dq_team_keys": [], 
        "score": 67, 
        "surrogate_team_keys": [], 
        "team_keys": [
          "frc1310", 
          "frc2702", 
          "frc7623"
        ]
      }, 
      "red": {
        "dq_team_keys": [], 
        "score": 48, 
        "surrogate_team_keys": [], 
        "team_keys": [
          "frc5409", 
          "frc9986", 
          "frc2609"
        ]
      }
    }, 
    "comp_level": "qm", 
    "event_key": "2019onha2", 
    "key": "2019onha2_qm18", 
    "match_number": 18, 
    "post_result_time": null, 
    "predicted_time": 1573400760, 
    "score_breakdown": null, 
    "set_number": 1, 
    "time": 1573400760, 
    "videos": [
      {
        "key": "Ce_dukkuYbk", 
        "type": "youtube"
      }
    ], 
    "winning_alliance": "blue"
  }, 
  {
    "actual_time": null, 
    "alliances": {
      "blue": {
        "dq_team_keys": [], 
        "score": 52, 
        "surrogate_team_keys": [], 
        "team_keys": [
          "frc4343", 
          "frc1360", 
          "frc5719"
        ]
      }, 
      "red": {
        "dq_team_keys": [], 
        "score": 95, 
        "surrogate_team_keys": [], 
        "team_keys": [
          "frc3015", 
          "frc4678", 
          "frc3683"
        ]
      }
    }, 
    "comp_level": "qm", 
    "event_key": "2019onha2", 
    "key": "2019onha2_qm19", 
    "match_number": 19, 
    "post_result_time": null, 
    "predicted_time": 1573401240, 
    "score_breakdown": null, 
    "set_number": 1, 
    "time": 1573401240, 
    "videos": [
      {
        "key": "uQ9d0oi6IUs", 
        "type": "youtube"
      }
    ], 
    "winning_alliance": "red"
  }, 
  {
    "actual_time": null, 
    "alliances": {
      "blue": {
        "dq_team_keys": [], 
        "score": 99, 
        "surrogate_team_keys": [], 
        "team_keys": [
          "frc3683", 
          "frc5719", 
          "frc1114"
        ]
      }, 
      "red": {
        "dq_team_keys": [], 
        "score": 38, 
        "surrogate_team_keys": [], 
        "team_keys": [
          "frc1285", 
          "frc4343", 
          "frc2013"
        ]
      }
    }, 
    "comp_level": "qm", 
    "event_key": "2019onha2", 
    "key": "2019onha2_qm2", 
    "match_number": 2, 
    "post_result_time": null, 
    "predicted_time": 1573393080, 
    "score_breakdown": null, 
    "set_number": 1, 
    "time": 1573393080, 
    "videos": [
      {
        "key": "zuqR7IevJO8", 
        "type": "youtube"
      }
    ], 
    "winning_alliance": "blue"
  }, 
  {
    "actual_time": null, 
    "alliances": {
      "blue": {
        "dq_team_keys": [], 
        "score": 82, 
        "surrogate_team_keys": [], 
        "team_keys": [
          "frc2013", 
          "frc4476", 
          "frc865"
        ]
      }, 
      "red": {
        "dq_team_keys": [], 
        "score": 32, 
        "surrogate_team_keys": [], 
        "team_keys": [
          "frc7022", 
          "frc7480", 
          "frc2604"
        ]
      }
    }, 
    "comp_level": "qm", 
    "event_key": "2019onha2", 
    "key": "2019onha2_qm20", 
    "match_number": 20, 
    "post_result_time": null, 
    "predicted_time": 1573401720, 
    "score_breakdown": null, 
    "set_number": 1, 
    "time": 1573401720, 
    "videos": [], 
    "winning_alliance": "blue"
  }, 
  {
    "actual_time": null, 
    "alliances": {
      "blue": {
        "dq_team_keys": [], 
        "score": 49, 
        "surrogate_team_keys": [], 
        "team_keys": [
          "frc3739", 
          "frc4992", 
          "frc1310"
        ]
      }, 
      "red": {
        "dq_team_keys": [], 
        "score": 70, 
        "surrogate_team_keys": [], 
        "team_keys": [
          "frc3683", 
          "frc1285", 
          "frc4917"
        ]
      }
    }, 
    "comp_level": "qm", 
    "event_key": "2019onha2", 
    "key": "2019onha2_qm21", 
    "match_number": 21, 
    "post_result_time": null, 
    "predicted_time": 1573402200, 
    "score_breakdown": null, 
    "set_number": 1, 
    "time": 1573402200, 
    "videos": [
      {
        "key": "MEmZl4KWNs4", 
        "type": "youtube"
      }
    ], 
    "winning_alliance": "red"
  }, 
  {
    "actual_time": null, 
    "alliances": {
      "blue": {
        "dq_team_keys": [], 
        "score": 78, 
        "surrogate_team_keys": [], 
        "team_keys": [
          "frc4343", 
          "frc3015", 
          "frc1241"
        ]
      }, 
      "red": {
        "dq_team_keys": [], 
        "score": 35, 
        "surrogate_team_keys": [], 
        "team_keys": [
          "frc9986", 
          "frc6336", 
          "frc7480"
        ]
      }
    }, 
    "comp_level": "qm", 
    "event_key": "2019onha2", 
    "key": "2019onha2_qm22", 
    "match_number": 22, 
    "post_result_time": null, 
    "predicted_time": 1573402680, 
    "score_breakdown": null, 
    "set_number": 1, 
    "time": 1573402680, 
    "videos": [
      {
        "key": "nZcwC6AoZNg", 
        "type": "youtube"
      }
    ], 
    "winning_alliance": "blue"
  }, 
  {
    "actual_time": null, 
    "alliances": {
      "blue": {
        "dq_team_keys": [], 
        "score": 47, 
        "surrogate_team_keys": [], 
        "team_keys": [
          "frc3161", 
          "frc1360", 
          "frc4678"
        ]
      }, 
      "red": {
        "dq_team_keys": [], 
        "score": 32, 
        "surrogate_team_keys": [], 
        "team_keys": [
          "frc1075", 
          "frc2604", 
          "frc7623"
        ]
      }
    }, 
    "comp_level": "qm", 
    "event_key": "2019onha2", 
    "key": "2019onha2_qm23", 
    "match_number": 23, 
    "post_result_time": null, 
    "predicted_time": 1573403160, 
    "score_breakdown": null, 
    "set_number": 1, 
    "time": 1573403160, 
    "videos": [
      {
        "key": "rivClObDFUE", 
        "type": "youtube"
      }
    ], 
    "winning_alliance": "blue"
  }, 
  {
    "actual_time": null, 
    "alliances": {
      "blue": {
        "dq_team_keys": [], 
        "score": 75, 
        "surrogate_team_keys": [], 
        "team_keys": [
          "frc7022", 
          "frc1114", 
          "frc2013"
        ]
      }, 
      "red": {
        "dq_team_keys": [], 
        "score": 60, 
        "surrogate_team_keys": [], 
        "team_keys": [
          "frc9985", 
          "frc865", 
          "frc5409"
        ]
      }
    }, 
    "comp_level": "qm", 
    "event_key": "2019onha2", 
    "key": "2019onha2_qm24", 
    "match_number": 24, 
    "post_result_time": null, 
    "predicted_time": 1573403640, 
    "score_breakdown": null, 
    "set_number": 1, 
    "time": 1573403640, 
    "videos": [], 
    "winning_alliance": "blue"
  }, 
  {
    "actual_time": null, 
    "alliances": {
      "blue": {
        "dq_team_keys": [], 
        "score": 61, 
        "surrogate_team_keys": [], 
        "team_keys": [
          "frc7509", 
          "frc5719", 
          "frc4476"
        ]
      }, 
      "red": {
        "dq_team_keys": [], 
        "score": 62, 
        "surrogate_team_keys": [], 
        "team_keys": [
          "frc2609", 
          "frc5912", 
          "frc2702"
        ]
      }
    }, 
    "comp_level": "qm", 
    "event_key": "2019onha2", 
    "key": "2019onha2_qm25", 
    "match_number": 25, 
    "post_result_time": null, 
    "predicted_time": 1573404120, 
    "score_breakdown": null, 
    "set_number": 1, 
    "time": 1573404120, 
    "videos": [
      {
        "key": "dXfoKNeMOOk", 
        "type": "youtube"
      }
    ], 
    "winning_alliance": "red"
  }, 
  {
    "actual_time": null, 
    "alliances": {
      "blue": {
        "dq_team_keys": [], 
        "score": 82, 
        "surrogate_team_keys": [], 
        "team_keys": [
          "frc1241", 
          "frc1310", 
          "frc4678"
        ]
      }, 
      "red": {
        "dq_team_keys": [], 
        "score": 39, 
        "surrogate_team_keys": [], 
        "team_keys": [
          "frc2013", 
          "frc9985", 
          "frc1360"
        ]
      }
    }, 
    "comp_level": "qm", 
    "event_key": "2019onha2", 
    "key": "2019onha2_qm26", 
    "match_number": 26, 
    "post_result_time": null, 
    "predicted_time": 1573408200, 
    "score_breakdown": null, 
    "set_number": 1, 
    "time": 1573408200, 
    "videos": [
      {
        "key": "P5KCRRAaWBs", 
        "type": "youtube"
      }
    ], 
    "winning_alliance": "blue"
  }, 
  {
    "actual_time": null, 
    "alliances": {
      "blue": {
        "dq_team_keys": [], 
        "score": 52, 
        "surrogate_team_keys": [], 
        "team_keys": [
          "frc5912", 
          "frc6336", 
          "frc5719"
        ]
      }, 
      "red": {
        "dq_team_keys": [], 
        "score": 41, 
        "surrogate_team_keys": [], 
        "team_keys": [
          "frc1114", 
          "frc2604", 
          "frc9986"
        ]
      }
    }, 
    "comp_level": "qm", 
    "event_key": "2019onha2", 
    "key": "2019onha2_qm27", 
    "match_number": 27, 
    "post_result_time": null, 
    "predicted_time": 1573408680, 
    "score_breakdown": null, 
    "set_number": 1, 
    "time": 1573408680, 
    "videos": [], 
    "winning_alliance": "blue"
  }, 
  {
    "actual_time": null, 
    "alliances": {
      "blue": {
        "dq_team_keys": [], 
        "score": 40, 
        "surrogate_team_keys": [], 
        "team_keys": [
          "frc7022", 
          "frc3739", 
          "frc2702"
        ]
      }, 
      "red": {
        "dq_team_keys": [], 
        "score": 53, 
        "surrogate_team_keys": [], 
        "team_keys": [
          "frc4992", 
          "frc7623", 
          "frc4343"
        ]
      }
    }, 
    "comp_level": "qm", 
    "event_key": "2019onha2", 
    "key": "2019onha2_qm28", 
    "match_number": 28, 
    "post_result_time": null, 
    "predicted_time": 1573409160, 
    "score_breakdown": null, 
    "set_number": 1, 
    "time": 1573409160, 
    "videos": [
      {
        "key": "17zT1M0uyqQ", 
        "type": "youtube"
      }
    ], 
    "winning_alliance": "red"
  }, 
  {
    "actual_time": null, 
    "alliances": {
      "blue": {
        "dq_team_keys": [], 
        "score": 89, 
        "surrogate_team_keys": [], 
        "team_keys": [
          "frc5409", 
          "frc3683", 
          "frc1075"
        ]
      }, 
      "red": {
        "dq_team_keys": [], 
        "score": 112, 
        "surrogate_team_keys": [], 
        "team_keys": [
          "frc4476", 
          "frc3015", 
          "frc4917"
        ]
      }
    }, 
    "comp_level": "qm", 
    "event_key": "2019onha2", 
    "key": "2019onha2_qm29", 
    "match_number": 29, 
    "post_result_time": null, 
    "predicted_time": 1573409640, 
    "score_breakdown": null, 
    "set_number": 1, 
    "time": 1573409640, 
    "videos": [
      {
        "key": "buelLiUwmhw", 
        "type": "youtube"
      }
    ], 
    "winning_alliance": "red"
  }, 
  {
    "actual_time": null, 
    "alliances": {
      "blue": {
        "dq_team_keys": [], 
        "score": 52, 
        "surrogate_team_keys": [], 
        "team_keys": [
          "frc7623", 
          "frc3161", 
          "frc5409"
        ]
      }, 
      "red": {
        "dq_team_keys": [], 
        "score": 44, 
        "surrogate_team_keys": [], 
        "team_keys": [
          "frc9985", 
          "frc4476", 
          "frc9986"
        ]
      }
    }, 
    "comp_level": "qm", 
    "event_key": "2019onha2", 
    "key": "2019onha2_qm3", 
    "match_number": 3, 
    "post_result_time": null, 
    "predicted_time": 1573393560, 
    "score_breakdown": null, 
    "set_number": 1, 
    "time": 1573393560, 
    "videos": [
      {
        "key": "w5UGNtH4nWI", 
        "type": "youtube"
      }
    ], 
    "winning_alliance": "blue"
  }, 
  {
    "actual_time": null, 
    "alliances": {
      "blue": {
        "dq_team_keys": [], 
        "score": 40, 
        "surrogate_team_keys": [], 
        "team_keys": [
          "frc1285", 
          "frc7509", 
          "frc2609"
        ]
      }, 
      "red": {
        "dq_team_keys": [], 
        "score": 68, 
        "surrogate_team_keys": [], 
        "team_keys": [
          "frc865", 
          "frc3161", 
          "frc7480"
        ]
      }
    }, 
    "comp_level": "qm", 
    "event_key": "2019onha2", 
    "key": "2019onha2_qm30", 
    "match_number": 30, 
    "post_result_time": null, 
    "predicted_time": 1573410120, 
    "score_breakdown": null, 
    "set_number": 1, 
    "time": 1573410120, 
    "videos": [
      {
        "key": "ccQNwZG6dCY", 
        "type": "youtube"
      }
    ], 
    "winning_alliance": "red"
  }, 
  {
    "actual_time": null, 
    "alliances": {
      "blue": {
        "dq_team_keys": [], 
        "score": 86, 
        "surrogate_team_keys": [], 
        "team_keys": [
          "frc6336", 
          "frc3683", 
          "frc1241"
        ]
      }, 
      "red": {
        "dq_team_keys": [], 
        "score": 47, 
        "surrogate_team_keys": [], 
        "team_keys": [
          "frc7623", 
          "frc5719", 
          "frc7022"
        ]
      }
    }, 
    "comp_level": "qm", 
    "event_key": "2019onha2", 
    "key": "2019onha2_qm31", 
    "match_number": 31, 
    "post_result_time": null, 
    "predicted_time": 1573410600, 
    "score_breakdown": null, 
    "set_number": 1, 
    "time": 1573410600, 
    "videos": [
      {
        "key": "FKzyY_rhWMY", 
        "type": "youtube"
      }
    ], 
    "winning_alliance": "blue"
  }, 
  {
    "actual_time": null, 
    "alliances": {
      "blue": {
        "dq_team_keys": [], 
        "score": 67, 
        "surrogate_team_keys": [], 
        "team_keys": [
          "frc2609", 
          "frc7480", 
          "frc4476"
        ]
      }, 
      "red": {
        "dq_team_keys": [], 
        "score": 68, 
        "surrogate_team_keys": [], 
        "team_keys": [
          "frc4992", 
          "frc1114", 
          "frc1360"
        ]
      }
    }, 
    "comp_level": "qm", 
    "event_key": "2019onha2", 
    "key": "2019onha2_qm32", 
    "match_number": 32, 
    "post_result_time": null, 
    "predicted_time": 1573411080, 
    "score_breakdown": null, 
    "set_number": 1, 
    "time": 1573411080, 
    "videos": [
      {
        "key": "vQfswGoF2BY", 
        "type": "youtube"
      }
    ], 
    "winning_alliance": "red"
  }, 
  {
    "actual_time": null, 
    "alliances": {
      "blue": {
        "dq_team_keys": [], 
        "score": 57, 
        "surrogate_team_keys": [], 
        "team_keys": [
          "frc9986", 
          "frc4917", 
          "frc5912"
        ]
      }, 
      "red": {
        "dq_team_keys": [], 
        "score": 62, 
        "surrogate_team_keys": [], 
        "team_keys": [
          "frc4678", 
          "frc2013", 
          "frc1075"
        ]
      }
    }, 
    "comp_level": "qm", 
    "event_key": "2019onha2", 
    "key": "2019onha2_qm33", 
    "match_number": 33, 
    "post_result_time": null, 
    "predicted_time": 1573411560, 
    "score_breakdown": null, 
    "set_number": 1, 
    "time": 1573411560, 
    "videos": [
      {
        "key": "0GB1o0vY528", 
        "type": "youtube"
      }
    ], 
    "winning_alliance": "red"
  }, 
  {
    "actual_time": null, 
    "alliances": {
      "blue": {
        "dq_team_keys": [], 
        "score": 71, 
        "surrogate_team_keys": [], 
        "team_keys": [
          "frc2702", 
          "frc9985", 
          "frc3015"
        ]
      }, 
      "red": {
        "dq_team_keys": [], 
        "score": 50, 
        "surrogate_team_keys": [], 
        "team_keys": [
          "frc1285", 
          "frc3739", 
          "frc865"
        ]
      }
    }, 
    "comp_level": "qm", 
    "event_key": "2019onha2", 
    "key": "2019onha2_qm34", 
    "match_number": 34, 
    "post_result_time": null, 
    "predicted_time": 1573412040, 
    "score_breakdown": null, 
    "set_number": 1, 
    "time": 1573412040, 
    "videos": [
      {
        "key": "3xa1DihwhqQ", 
        "type": "youtube"
      }
    ], 
    "winning_alliance": "blue"
  }, 
  {
    "actual_time": null, 
    "alliances": {
      "blue": {
        "dq_team_keys": [], 
        "score": 41, 
        "surrogate_team_keys": [], 
        "team_keys": [
          "frc4343", 
          "frc2604", 
          "frc3161"
        ]
      }, 
      "red": {
        "dq_team_keys": [], 
        "score": 55, 
        "surrogate_team_keys": [], 
        "team_keys": [
          "frc1310", 
          "frc7509", 
          "frc5409"
        ]
      }
    }, 
    "comp_level": "qm", 
    "event_key": "2019onha2", 
    "key": "2019onha2_qm35", 
    "match_number": 35, 
    "post_result_time": null, 
    "predicted_time": 1573412520, 
    "score_breakdown": null, 
    "set_number": 1, 
    "time": 1573412520, 
    "videos": [
      {
        "key": "DTL0t3se59E", 
        "type": "youtube"
      }
    ], 
    "winning_alliance": "red"
  }, 
  {
    "actual_time": null, 
    "alliances": {
      "blue": {
        "dq_team_keys": [], 
        "score": 38, 
        "surrogate_team_keys": [], 
        "team_keys": [
          "frc1360", 
          "frc3739", 
          "frc6336"
        ]
      }, 
      "red": {
        "dq_team_keys": [], 
        "score": 74, 
        "surrogate_team_keys": [], 
        "team_keys": [
          "frc4917", 
          "frc865", 
          "frc7509"
        ]
      }
    }, 
    "comp_level": "qm", 
    "event_key": "2019onha2", 
    "key": "2019onha2_qm4", 
    "match_number": 4, 
    "post_result_time": null, 
    "predicted_time": 1573394040, 
    "score_breakdown": null, 
    "set_number": 1, 
    "time": 1573394040, 
    "videos": [
      {
        "key": "L2ZIA96Nv4M", 
        "type": "youtube"
      }
    ], 
    "winning_alliance": "red"
  }, 
  {
    "actual_time": null, 
    "alliances": {
      "blue": {
        "dq_team_keys": [], 
        "score": 73, 
        "surrogate_team_keys": [], 
        "team_keys": [
          "frc5912", 
          "frc7022", 
          "frc1075"
        ]
      }, 
      "red": {
        "dq_team_keys": [], 
        "score": 59, 
        "surrogate_team_keys": [], 
        "team_keys": [
          "frc3015", 
          "frc2609", 
          "frc1310"
        ]
      }
    }, 
    "comp_level": "qm", 
    "event_key": "2019onha2", 
    "key": "2019onha2_qm5", 
    "match_number": 5, 
    "post_result_time": null, 
    "predicted_time": 1573394520, 
    "score_breakdown": null, 
    "set_number": 1, 
    "time": 1573394520, 
    "videos": [
      {
        "key": "3IUeRqGiE-0", 
        "type": "youtube"
      }
    ], 
    "winning_alliance": "blue"
  }, 
  {
    "actual_time": null, 
    "alliances": {
      "blue": {
        "dq_team_keys": [], 
        "score": 69, 
        "surrogate_team_keys": [], 
        "team_keys": [
          "frc3161", 
          "frc4992", 
          "frc4476"
        ]
      }, 
      "red": {
        "dq_team_keys": [], 
        "score": 64, 
        "surrogate_team_keys": [], 
        "team_keys": [
          "frc5719", 
          "frc865", 
          "frc1241"
        ]
      }
    }, 
    "comp_level": "qm", 
    "event_key": "2019onha2", 
    "key": "2019onha2_qm6", 
    "match_number": 6, 
    "post_result_time": null, 
    "predicted_time": 1573395000, 
    "score_breakdown": null, 
    "set_number": 1, 
    "time": 1573395000, 
    "videos": [
      {
        "key": "nL3jBr1wxJ0", 
        "type": "youtube"
      }
    ], 
    "winning_alliance": "blue"
  }, 
  {
    "actual_time": null, 
    "alliances": {
      "blue": {
        "dq_team_keys": [], 
        "score": 53, 
        "surrogate_team_keys": [], 
        "team_keys": [
          "frc2604", 
          "frc5409", 
          "frc6336"
        ]
      }, 
      "red": {
        "dq_team_keys": [], 
        "score": 30, 
        "surrogate_team_keys": [], 
        "team_keys": [
          "frc3739", 
          "frc2609", 
          "frc4678"
        ]
      }
    }, 
    "comp_level": "qm", 
    "event_key": "2019onha2", 
    "key": "2019onha2_qm7", 
    "match_number": 7, 
    "post_result_time": null, 
    "predicted_time": 1573395480, 
    "score_breakdown": null, 
    "set_number": 1, 
    "time": 1573395480, 
    "videos": [
      {
        "key": "zd0t4o8CGyw", 
        "type": "youtube"
      }
    ], 
    "winning_alliance": "blue"
  }, 
  {
    "actual_time": null, 
    "alliances": {
      "blue": {
        "dq_team_keys": [], 
        "score": 64, 
        "surrogate_team_keys": [], 
        "team_keys": [
          "frc7623", 
          "frc5912", 
          "frc9985"
        ]
      }, 
      "red": {
        "dq_team_keys": [], 
        "score": 36, 
        "surrogate_team_keys": [], 
        "team_keys": [
          "frc7480", 
          "frc1075", 
          "frc4343"
        ]
      }
    }, 
    "comp_level": "qm", 
    "event_key": "2019onha2", 
    "key": "2019onha2_qm8", 
    "match_number": 8, 
    "post_result_time": null, 
    "predicted_time": 1573395960, 
    "score_breakdown": null, 
    "set_number": 1, 
    "time": 1573395960, 
    "videos": [
      {
        "key": "0WdGmkujInQ", 
        "type": "youtube"
      }
    ], 
    "winning_alliance": "blue"
  }, 
  {
    "actual_time": null, 
    "alliances": {
      "blue": {
        "dq_team_keys": [], 
        "score": 60, 
        "surrogate_team_keys": [], 
        "team_keys": [
          "frc3015", 
          "frc7509", 
          "frc1114"
        ]
      }, 
      "red": {
        "dq_team_keys": [], 
        "score": 61, 
        "surrogate_team_keys": [], 
        "team_keys": [
          "frc1310", 
          "frc2013", 
          "frc3683"
        ]
      }
    }, 
    "comp_level": "qm", 
    "event_key": "2019onha2", 
    "key": "2019onha2_qm9", 
    "match_number": 9, 
    "post_result_time": null, 
    "predicted_time": 1573396440, 
    "score_breakdown": null, 
    "set_number": 1, 
    "time": 1573396440, 
    "videos": [
      {
        "key": "ifw9mz3ELlc", 
        "type": "youtube"
      }
    ], 
    "winning_alliance": "red"
  }, 
  {
    "actual_time": null, 
    "alliances": {
      "blue": {
        "dq_team_keys": [], 
        "score": 43, 
        "surrogate_team_keys": [], 
        "team_keys": [
          "frc3739", 
          "frc1075", 
          "frc5409"
        ]
      }, 
      "red": {
        "dq_team_keys": [], 
        "score": 82, 
        "surrogate_team_keys": [], 
        "team_keys": [
          "frc1114", 
          "frc7509", 
          "frc3683"
        ]
      }
    }, 
    "comp_level": "sf", 
    "event_key": "2019onha2", 
    "key": "2019onha2_sf1m1", 
    "match_number": 1, 
    "post_result_time": null, 
    "predicted_time": null, 
    "score_breakdown": null, 
    "set_number": 1, 
    "time": null, 
    "videos": [
      {
        "key": "5k2KEsSjBYg", 
        "type": "youtube"
      }
    ], 
    "winning_alliance": "red"
  }, 
  {
    "actual_time": null, 
    "alliances": {
      "blue": {
        "dq_team_keys": [], 
        "score": 65, 
        "surrogate_team_keys": [], 
        "team_keys": [
          "frc3739", 
          "frc1075", 
          "frc5409"
        ]
      }, 
      "red": {
        "dq_team_keys": [], 
        "score": 102, 
        "surrogate_team_keys": [], 
        "team_keys": [
          "frc1114", 
          "frc7509", 
          "frc3683"
        ]
      }
    }, 
    "comp_level": "sf", 
    "event_key": "2019onha2", 
    "key": "2019onha2_sf1m2", 
    "match_number": 2, 
    "post_result_time": null, 
    "predicted_time": null, 
    "score_breakdown": null, 
    "set_number": 1, 
    "time": null, 
    "videos": [
      {
        "key": "mv47UYdP5X8", 
        "type": "youtube"
      }
    ], 
    "winning_alliance": "red"
  }, 
  {
    "actual_time": null, 
    "alliances": {
      "blue": {
        "dq_team_keys": [], 
        "score": 71, 
        "surrogate_team_keys": [], 
        "team_keys": [
          "frc4917", 
          "frc6336", 
          "frc1310"
        ]
      }, 
      "red": {
        "dq_team_keys": [], 
        "score": 100, 
        "surrogate_team_keys": [], 
        "team_keys": [
          "frc3015", 
          "frc5719", 
          "frc4476"
        ]
      }
    }, 
    "comp_level": "sf", 
    "event_key": "2019onha2", 
    "key": "2019onha2_sf2m1", 
    "match_number": 1, 
    "post_result_time": null, 
    "predicted_time": null, 
    "score_breakdown": null, 
    "set_number": 2, 
    "time": null, 
    "videos": [], 
    "winning_alliance": "red"
  }, 
  {
    "actual_time": null, 
    "alliances": {
      "blue": {
        "dq_team_keys": [], 
        "score": 62, 
        "surrogate_team_keys": [], 
        "team_keys": [
          "frc4917", 
          "frc6336", 
          "frc1310"
        ]
      }, 
      "red": {
        "dq_team_keys": [], 
        "score": 98, 
        "surrogate_team_keys": [], 
        "team_keys": [
          "frc3015", 
          "frc5719", 
          "frc4476"
        ]
      }
    }, 
    "comp_level": "sf", 
    "event_key": "2019onha2", 
    "key": "2019onha2_sf2m2", 
    "match_number": 2, 
    "post_result_time": null, 
    "predicted_time": null, 
    "score_breakdown": null, 
    "set_number": 2, 
    "time": null, 
    "videos": [
      {
        "key": "qcjR-rrdMpw", 
        "type": "youtube"
      }, 
      {
        "key": "4J1KpDyJBWE", 
        "type": "youtube"
      }
    ], 
    "winning_alliance": "red"
  }
]
